davidkhala/logtail/__init__.py
davidkhala/logtail/__pycache__/__init__.cpython-313.pyc
davidkhala/mezmo/__init__.py
davidkhala/mezmo/__pycache__/__init__.cpython-313.pyc
davidkhala/newrelic/__init__.py
davidkhala/newrelic/__pycache__/__init__.cpython-313.pyc
davidkhala/newrelic/__pycache__/log.cpython-313.pyc
davidkhala/newrelic/log.py
davidkhala_devops-0.0.3.dist-info/METADATA
davidkhala_devops-0.0.3.dist-info/WHEEL
davidkhala_devops-0.0.3.dist-info/RECORD
