Metadata-Version: 2.3
Name: davidkhala.devops
Version: 0.0.3
Summary: @davidkhala/devops
Author: David Liu
Author-email: david-khala@hotmail.com
Requires-Python: >=3.10,<4.0
Classifier: Programming Language :: Python :: 3
Classifier: Programming Language :: Python :: 3.10
Classifier: Programming Language :: Python :: 3.11
Classifier: Programming Language :: Python :: 3.12
Classifier: Programming Language :: Python :: 3.13
Provides-Extra: better-stack
Provides-Extra: mezmo
Provides-Extra: new-relic
Requires-Dist: davidkhala-utils
Requires-Dist: logdna ; extra == "mezmo"
Requires-Dist: logtail-python ; extra == "better-stack"
Requires-Dist: newrelic-telemetry-sdk ; extra == "new-relic"
